thousandeyes_sdk/event_detection/__init__.py
thousandeyes_sdk/event_detection/py.typed
thousandeyes_sdk/event_detection/api/__init__.py
thousandeyes_sdk/event_detection/api/events_api.py
thousandeyes_sdk/event_detection/models/__init__.py
thousandeyes_sdk/event_detection/models/affected_agents.py
thousandeyes_sdk/event_detection/models/affected_count.py
thousandeyes_sdk/event_detection/models/affected_targets.py
thousandeyes_sdk/event_detection/models/affected_tests.py
thousandeyes_sdk/event_detection/models/agent_links.py
thousandeyes_sdk/event_detection/models/agent_local_event_detail.py
thousandeyes_sdk/event_detection/models/agent_local_event_grouping.py
thousandeyes_sdk/event_detection/models/api_affected_target.py
thousandeyes_sdk/event_detection/models/cloud_enterprise_agent_type.py
thousandeyes_sdk/event_detection/models/dns_event_detail.py
thousandeyes_sdk/event_detection/models/dns_event_grouping.py
thousandeyes_sdk/event_detection/models/error.py
thousandeyes_sdk/event_detection/models/event.py
thousandeyes_sdk/event_detection/models/event_alert_severity.py
thousandeyes_sdk/event_detection/models/event_api_affected_agent.py
thousandeyes_sdk/event_detection/models/event_api_affected_test.py
thousandeyes_sdk/event_detection/models/event_detail.py
thousandeyes_sdk/event_detection/models/event_detail_base.py
thousandeyes_sdk/event_detection/models/event_state.py
thousandeyes_sdk/event_detection/models/event_test_links.py
thousandeyes_sdk/event_detection/models/event_type.py
thousandeyes_sdk/event_detection/models/events.py
thousandeyes_sdk/event_detection/models/link.py
thousandeyes_sdk/event_detection/models/network_event_detail.py
thousandeyes_sdk/event_detection/models/network_event_grouping.py
thousandeyes_sdk/event_detection/models/network_pop_event_detail.py
thousandeyes_sdk/event_detection/models/pagination_next_and_self_links.py
thousandeyes_sdk/event_detection/models/proxy_event_detail.py
thousandeyes_sdk_event_detection-2.23.0.dist-info/licenses/LICENSE
thousandeyes_sdk_event_detection-2.23.0.dist-info/licenses/NOTICE
thousandeyes_sdk_event_detection-2.23.0.dist-info/METADATA
thousandeyes_sdk_event_detection-2.23.0.dist-info/WHEEL
thousandeyes_sdk_event_detection-2.23.0.dist-info/top_level.txt
thousandeyes_sdk_event_detection-2.23.0.dist-info/RECORD
